hikari_bot/__init__.py
hikari_bot/data_source.py
hikari_bot/game/minimap_renderer.py
hikari_bot/game/ocr.py
hikari_bot/game/pupu.py
hikari_bot/utils.py
hikari_bot-1.0.9.dist-info/LICENSE
hikari_bot-1.0.9.dist-info/METADATA
hikari_bot-1.0.9.dist-info/WHEEL
hikari_bot-1.0.9.dist-info/RECORD
